bgfactory/ff.py
bgfactory/common/config.py
bgfactory/common/profiler.py
bgfactory/components/cairo_helpers.py
bgfactory/components/card_sheet.py
bgfactory/components/component.py
bgfactory/components/constants.py
bgfactory/components/grid.py
bgfactory/components/pango_helpers.py
bgfactory/components/regular_polygon.py
bgfactory/components/shape.py
bgfactory/components/source.py
bgfactory/components/test text bounds.py
bgfactory/components/test_surface_source.py
bgfactory/components/text.py
bgfactory/components/transformations.py
bgfactory/components/utils.py
bgfactory/components/layout/absolute_layout.py
bgfactory/components/layout/horizontal_flow_layout.py
bgfactory/components/layout/layout_manager.py
bgfactory/components/layout/vertical_flow_layout.py
tests/__init__.py
tests/generate_reference.py
tests/test_grid.py
tests/test_horizontal_flow_layout2.py
tests/test_regular_polygon.py
tests/test_text_alignment.py
tests/test_text_markup.py
tests/test_text_uniform.py
tests/test_vertical_flow_layout.py
tests/test_vertical_flow_layout2.py
tests/utils.py
board_game_factory-0.3.0.dist-info/LICENSE.txt
board_game_factory-0.3.0.dist-info/METADATA
board_game_factory-0.3.0.dist-info/WHEEL
board_game_factory-0.3.0.dist-info/top_level.txt
board_game_factory-0.3.0.dist-info/RECORD
