Metadata-Version: 2.1
Name: board-game-factory
Version: 0.3.0
Summary: Board Game Factory - a framework for creating and scaling up production of vector graphics assets, e.g. for board games.
Home-page: https://github.com/avolny/board-game-factory
Author: Adam Volný
Author-email: adam.volny@gmail.com
Project-URL: Bug Tracker, https://github.com/avolny/board-game-factory/issues
Classifier: Programming Language :: Python :: 3
Classifier: License :: OSI Approved :: MIT License
Classifier: Operating System :: OS Independent
Classifier: Topic :: Multimedia :: Graphics
Requires-Python: >=3.6
License-File: LICENSE.txt
Requires-Dist: pangocairocffi
Requires-Dist: cairocffi
Requires-Dist: pangocffi
Requires-Dist: pillow
Requires-Dist: numpy
